{
	"app_title": "GC Media",
	"bugatti_api_endpoint" : "http://localhost:3000",
	"default_background_color": "#E3342F",
	"pages" : [
		{
			"title" : "Home",
			"subtitle" : "View the latest uploads",
			"route" : "/"
		},
		{
			"title" : "Upload",
			"subtitle" : "Upload a new image or video",
			"route" : "/upload"
		},
		{
			"title" : "Quotes",
			"subtitle" : "View quotes from the GC",
			"route" : "/quotes"
		},
		{
			"title" : "Search",
			"subtitle" : "Find images, videos, and quotes",
			"route" : "/search"
		},
		{
			"title" : "Members",
			"subtitle" : "View the GC members",
			"route" : "/members"
		}
	]
}